{
    "config": {
        "postsPerPage": 4,
        "tagsPostsPerPage": 4,
        "authorsPostsPerPage": 5,
        "excerptLength": 45,
        "logo": ""
    },
    "customConfig": {
        "navbarHeight": "5.25rem",
        "entryWidth": "62ch",
        "navWidth": "300px",
        "frontSource": "default",
        "frontPost": "",
        "frontGallery": false,
        "listingDate": false,
        "listingAuthor": false,
        "heroHeight": "40vh",
        "heroBg": "#000000",
        "displayHeroImage": true,
        "uploadHero": "",
        "uploadHeroAlt": "",
        "uploadHeroCaption": "",
        "heroOverlay": "rgba(0, 0, 0, 0.2)",
        "imageEffects": false,
        "imageFilter": "saturate",
        "imageFilterValue": "1",
        "textHero": "<h1>Joshuadesir.life</h1>\n<p> </p>",
        "heroTextColor": "#FFFFFF",
        "heroBorderColor": "rgba(255, 255, 255, 0.2)",
        "primaryColor": "#A6752E",
        "headingsColor": "#262626",
        "textColor": "#262626",
        "navBg": "#000000",
        "navLinkColor": "#9D9D9D",
        "navLinkColorHover": "#FFFFFF",
        "logoColor": "#ffffff",
        "fontFamily": "font-pair-11",
        "minFontSize": "1",
        "maxFontSize": "1.5",
        "fontNormalWeight": "400",
        "fontBoldWeight": "700",
        "lineHeight": "1.6",
        "fontHeadignsWeight": "700",
        "fontHeadingsTransform": "none",
        "shareFacebook": true,
        "shareTwitter": true,
        "shareTwitterName": "",
        "sharePinterest": true,
        "shareMix": true,
        "shareLinkedin": true,
        "shareBuffer": true,
        "shareWhatsApp": true,
        "commentDisqusShortname": "",
        "copyrightText": "Copyright 2021 Joshuadesir.life",
        "socialButtons": false,
        "socialFacebook": "",
        "socialTwitter": "",
        "socialInstagram": "",
        "socialLinkedin": "",
        "socialVimeo": "",
        "socialPinterest": "",
        "socialYoutube": "",
        "galleryItemGap": "0.53333rem",
        "galleryLightboxStyle": "pswp--dark",
        "galleryLightboxOpacity": "0.7",
        "galleryAdvanced": true,
        "galleryCounter": true,
        "galleryZoom": true,
        "galleryFullscreen": true,
        "galleryShare": true,
        "galleryClose": true,
        "galleryArrows": true,
        "galleryPreloader": true,
        "galleryCloseOnScroll": true,
        "galleryArrowKeys": true,
        "formatDate": "dddd, MMMM D, YYYY",
        "formatDateCustom": "HH:mm:ss YY/MM/DD",
        "lazyLoadEffect": "fadein",
        "faviconUpload": "",
        "faviconExtension": "image/x-icon"
    },
    "postConfig": {
        "displayAuthor": 1,
        "displayDate": 1,
        "displayShareButtons": 1,
        "displayTags": 1,
        "displayAuthorBio": 1,
        "displayComments": 0
    },
    "defaultTemplates": {
        "post": ""
    }
}